hw_weather_server/__init__.py
hw_weather_server/client.py
hw_weather_server/server.py
hw_weather_server-0.1.0.dist-info/METADATA
hw_weather_server-0.1.0.dist-info/WHEEL
hw_weather_server-0.1.0.dist-info/entry_points.txt
hw_weather_server-0.1.0.dist-info/RECORD
