Metadata-Version: 2.4
Name: hw-weather-server
Version: 0.1.0
Summary: search weather by location
Author-email: wenzw <wenzw@huaweisoft.com>
Requires-Python: >=3.12
Requires-Dist: mcp>=1.9.1
